[
	{
		"id": 1,
		"name": "Abaddon",
		"image": "./heroes/abaddon.png",
		"attr": "strength"
	},
	{
		"id": 2,
		"name": "Alchemist",
		"image": "./heroes/alchemist.png",
		"attr": "strength"
	},
	{
		"id": 3,
		"name": "Axe",
		"image": "./heroes/axe.png",
		"attr": "strength"
	},
	{
		"id": 4,
		"name": "Beastmaster",
		"image": "./heroes/beastmaster.png",
		"attr": "strength"
	},
	{
		"id": 5,
		"name": "Brewmaster",
		"image": "./heroes/brewmaster.png",
		"attr": "strength"
	},
	{
		"id": 6,
		"name": "Bristleback",
		"image": "./heroes/bristleback.png",
		"attr": "strength"
	},
	{
		"id": 7,
		"name": "Centaur Warrunner",
		"image": "./heroes/Centaur Warrunner.png",
		"attr": "strength"
	},
	{
		"id": 8,
		"name": "Chaos Knight",
		"image": "./heroes/Chaos Knight.png",
		"attr": "strength"
	},
	{
		"id": 9,
		"name": "Clockwerk",
		"image": "./heroes/Clockwerk.png",
		"attr": "strength"
	},
	{
		"id": 10,
		"name": "Dawnbreaker",
		"image": "./heroes/Dawnbreaker.png",
		"attr": "strength"
	},
	{
		"id": 11,
		"name": "Doom",
		"image": "./heroes/Doom.png",
		"attr": "strength"
	},
	{
		"id": 12,
		"name": "Dragon Knight",
		"image": "./heroes/Dragon Knight.png",
		"attr": "strength"
	},
	{
		"id": 13,
		"name": "Earth Spirit",
		"image": "./heroes/Earth Spirit.png",
		"attr": "strength"
	},
	{
		"id": 14,
		"name": "Earthshaker",
		"image": "./heroes/Earthshaker.png",
		"attr": "strength"
	},
	{
		"id": 15,
		"name": "Elder Titan",
		"image": "./heroes/Elder Titan.png",
		"attr": "strength"
	},
	{
		"id": 16,
		"name": "Huskar",
		"image": "./heroes/Huskar.png",
		"attr": "strength"
	},
	{
		"id": 17,
		"name": "Io",
		"image": "./heroes/Io.png",
		"attr": "strength"
	},
	{
		"id": 18,
		"name": "Kunkka",
		"image": "./heroes/Kunkka.png",
		"attr": "strength"
	},
	{
		"id": 19,
		"name": "Legion Commander",
		"image": "./heroes/Legion Commander.png",
		"attr": "strength"
	},
	{
		"id": 20,
		"name": "Lifestealer",
		"image": "./heroes/Lifestealer.png",
		"attr": "strength"
	},
	{
		"id": 21,
		"name": "Lycan",
		"image": "./heroes/Lycan.png",
		"attr": "strength"
	},
	{
		"id": 22,
		"name": "Magnus",
		"image": "./heroes/Magnus.png",
		"attr": "strength"
	},
	{
		"id": 23,
		"name": "Marci",
		"image": "./heroes/Marci.png",
		"attr": "strength"
	},
	{
		"id": 24,
		"name": "Mars",
		"image": "./heroes/Mars.png",
		"attr": "strength"
	},
	{
		"id": 25,
		"name": "Night Stalker",
		"image": "./heroes/Night Stalker.png",
		"attr": "strength"
	},
	{
		"id": 26,
		"name": "Omniknight",
		"image": "./heroes/Omniknight.png",
		"attr": "strength"
	},
	{
		"id": 27,
		"name": "Phoenix",
		"image": "./heroes/Phoenix.png",
		"attr": "strength"
	},
	{
		"id": 28,
		"name": "Pudge",
		"image": "./heroes/Pudge.png",
		"attr": "strength"
	},
	{
		"id": 29,
		"name": "Sand King",
		"image": "./heroes/Sand King.png",
		"attr": "strength"
	},
	{
		"id": 30,
		"name": "Slardar",
		"image": "./heroes/Slardar.png",
		"attr": "strength"
	},
	{
		"id": 31,
		"name": "Snapfire",
		"image": "./heroes/Snapfire.png",
		"attr": "strength"
	},
	{
		"id": 32,
		"name": "Spirit Breaker",
		"image": "./heroes/Spirit Breaker.png",
		"attr": "strength"
	},
	{
		"id": 33,
		"name": "Sven",
		"image": "./heroes/Sven.png",
		"attr": "strength"
	},
	{
		"id": 34,
		"name": "Tidehunter",
		"image": "./heroes/Tidehunter.png",
		"attr": "strength"
	},
	{
		"id": 35,
		"name": "Timbersaw",
		"image": "./heroes/Timbersaw.png",
		"attr": "strength"
	},
	{
		"id": 36,
		"name": "Tiny",
		"image": "./heroes/Tiny.png",
		"attr": "strength"
	},
	{
		"id": 37,
		"name": "Treant Protector",
		"image": "./heroes/Treant Protector.png",
		"attr": "strength"
	},
	{
		"id": 38,
		"name": "Tusk",
		"image": "./heroes/Tusk.png",
		"attr": "strength"
	},
	{
		"id": 39,
		"name": "Underlord",
		"image": "./heroes/Underlord.png",
		"attr": "strength"
	},
	{
		"id": 40,
		"name": "Undying",
		"image": "./heroes/Undying.png",
		"attr": "strength"
	},
	{
		"id": 41,
		"name": "Wraith King",
		"image": "./heroes/Wraith King.png",
		"attr": "strength"
	},
	{
		"id": 42,
		"name": "Anti-Mage",
		"image": "./heroes/Anti-Mage.png",
		"attr": "agi"
	},
	{
		"id": 43,
		"name": "Arc Warden",
		"image": "./heroes/Arc Warden.png",
		"attr": "agi"
	},
	{
		"id": 44,
		"name": "Bloodseeker",
		"image": "./heroes/Bloodseeker.png",
		"attr": "agi"
	},
	{
		"id": 45,
		"name": "Bounty Hunter",
		"image": "./heroes/Bounty Hunter.png",
		"attr": "agi"
	},
	{
		"id": 46,
		"name": "Broodmother",
		"image": "./heroes/Broodmother.png",
		"attr": "agi"
	},
	{
		"id": 47,
		"name": "Clinkz",
		"image": "./heroes/Clinkz.png",
		"attr": "agi"
	},
	{
		"id": 48,
		"name": "Drow Ranger",
		"image": "./heroes/Drow Ranger.png",
		"attr": "agi"
	},
	{
		"id": 49,
		"name": "Ember Spirit",
		"image": "./heroes/Ember Spirit.png",
		"attr": "agi"
	},
	{
		"id": 50,
		"name": "Faceless Void",
		"image": "./heroes/Faceless Void.png",
		"attr": "agi"
	},
	{
		"id": 51,
		"name": "Gyrocopter",
		"image": "./heroes/Gyrocopter.png",
		"attr": "agi"
	},
	{
		"id": 52,
		"name": "Hoodwink",
		"image": "./heroes/Hoodwink.png",
		"attr": "agi"
	},
	{
		"id": 53,
		"name": "Juggernaut",
		"image": "./heroes/Juggernaut.png",
		"attr": "agi"
	},
	{
		"id": 54,
		"name": "Lone Druid",
		"image": "./heroes/Lone Druid.png",
		"attr": "agi"
	},
	{
		"id": 55,
		"name": "Luna",
		"image": "./heroes/Luna.png",
		"attr": "agi"
	},
	{
		"id": 56,
		"name": "Medusa",
		"image": "./heroes/Medusa.png",
		"attr": "agi"
	},
	{
		"id": 57,
		"name": "Meepo",
		"image": "./heroes/Meepo.png",
		"attr": "agi"
	},
	{
		"id": 58,
		"name": "Mirana",
		"image": "./heroes/Mirana.png",
		"attr": "agi"
	},
	{
		"id": 59,
		"name": "Monkey King",
		"image": "./heroes/Monkey King.png",
		"attr": "agi"
	},
	{
		"id": 60,
		"name": "Morphling",
		"image": "./heroes/Morphling.png",
		"attr": "agi"
	},
	{
		"id": 61,
		"name": "Naga Siren",
		"image": "./heroes/Naga Siren.png",
		"attr": "agi"
	},
	{
		"id": 62,
		"name": "Pangolier",
		"image": "./heroes/Pangolier.png",
		"attr": "agi"
	},
	{
		"id": 63,
		"name": "Phantom Assassin",
		"image": "./heroes/Phantom Assassin.png",
		"attr": "agi"
	},
	{
		"id": 64,
		"name": "Phantom Lancer",
		"image": "./heroes/Phantom Lancer.png",
		"attr": "agi"
	},
	{
		"id": 65,
		"name": "Razor",
		"image": "./heroes/Razor.png",
		"attr": "agi"
	},
	{
		"id": 66,
		"name": "Riki",
		"image": "./heroes/Riki.png",
		"attr": "agi"
	},
	{
		"id": 67,
		"name": "Shadow Fiend",
		"image": "./heroes/Shadow Fiend.png",
		"attr": "agi"
	},
	{
		"id": 68,
		"name": "Slark",
		"image": "./heroes/Slark.png",
		"attr": "agi"
	},
	{
		"id": 69,
		"name": "Sniper",
		"image": "./heroes/Sniper.png",
		"attr": "agi"
	},
	{
		"id": 70,
		"name": "Spectre",
		"image": "./heroes/Spectre.png",
		"attr": "agi"
	},
	{
		"id": 71,
		"name": "Templar Assassin",
		"image": "./heroes/Templar Assassin.png",
		"attr": "agi"
	},
	{
		"id": 72,
		"name": "Terrorblade",
		"image": "./heroes/Terrorblade.png",
		"attr": "agi"
	},
	{
		"id": 73,
		"name": "Troll Warlord",
		"image": "./heroes/Troll Warlord.png",
		"attr": "agi"
	},
	{
		"id": 74,
		"name": "Ursa",
		"image": "./heroes/Ursa.png",
		"attr": "agi"
	},
	{
		"id": 75,
		"name": "Vengeful Spirit",
		"image": "./heroes/Vengeful Spirit.png",
		"attr": "agi"
	},
	{
		"id": 76,
		"name": "Venomancer",
		"image": "./heroes/Venomancer.png",
		"attr": "agi"
	},
	{
		"id": 77,
		"name": "Viper",
		"image": "./heroes/Viper.png",
		"attr": "agi"
	},
	{
		"id": 78,
		"name": "Weaver",
		"image": "./heroes/Weaver.png",
		"attr": "agi"
	}
]